mrpro/VERSION
mrpro/__init__.py
mrpro/_version.py
mrpro/py.typed
mrpro/algorithms/__init__.py
mrpro/algorithms/prewhiten_kspace.py
mrpro/algorithms/csm/__init__.py
mrpro/algorithms/csm/inati.py
mrpro/algorithms/csm/walsh.py
mrpro/algorithms/dcf/__init__.py
mrpro/algorithms/dcf/dcf_voronoi.py
mrpro/algorithms/optimizers/OptimizerStatus.py
mrpro/algorithms/optimizers/__init__.py
mrpro/algorithms/optimizers/adam.py
mrpro/algorithms/optimizers/cg.py
mrpro/algorithms/optimizers/lbfgs.py
mrpro/algorithms/optimizers/pdhg.py
mrpro/algorithms/optimizers/pgd.py
mrpro/algorithms/reconstruction/DirectReconstruction.py
mrpro/algorithms/reconstruction/IterativeSENSEReconstruction.py
mrpro/algorithms/reconstruction/Reconstruction.py
mrpro/algorithms/reconstruction/RegularizedIterativeSENSEReconstruction.py
mrpro/algorithms/reconstruction/__init__.py
mrpro/data/AcqInfo.py
mrpro/data/CsmData.py
mrpro/data/Dataclass.py
mrpro/data/DcfData.py
mrpro/data/EncodingLimits.py
mrpro/data/IData.py
mrpro/data/IHeader.py
mrpro/data/KData.py
mrpro/data/KHeader.py
mrpro/data/KNoise.py
mrpro/data/KTrajectory.py
mrpro/data/QData.py
mrpro/data/QHeader.py
mrpro/data/Rotation.py
mrpro/data/SpatialDimension.py
mrpro/data/__init__.py
mrpro/data/acq_filters.py
mrpro/data/enums.py
mrpro/data/traj_calculators/KTrajectoryCalculator.py
mrpro/data/traj_calculators/KTrajectoryCartesian.py
mrpro/data/traj_calculators/KTrajectoryIsmrmrd.py
mrpro/data/traj_calculators/KTrajectoryPulseq.py
mrpro/data/traj_calculators/KTrajectoryRadial2D.py
mrpro/data/traj_calculators/KTrajectoryRpe.py
mrpro/data/traj_calculators/KTrajectorySpiral2D.py
mrpro/data/traj_calculators/KTrajectorySunflowerGoldenRpe.py
mrpro/data/traj_calculators/__init__.py
mrpro/operators/AveragingOp.py
mrpro/operators/CartesianSamplingOp.py
mrpro/operators/ConjugateGradientOp.py
mrpro/operators/ConstraintsOp.py
mrpro/operators/DensityCompensationOp.py
mrpro/operators/DictionaryMatchOp.py
mrpro/operators/EinsumOp.py
mrpro/operators/EndomorphOperator.py
mrpro-0.250812.dist-info/licenses/LICENSE
mrpro-0.250812.dist-info/METADATA
mrpro-0.250812.dist-info/WHEEL
mrpro-0.250812.dist-info/top_level.txt
mrpro-0.250812.dist-info/RECORD
