Metadata-Version: 2.4
Name: mrpro
Version: 0.250812
Summary: MR image reconstruction and processing package specifically developed for PyTorch.
Author-email: MRpro Team <info@emerpro.de>, Christoph Kolbitsch <christoph.kolbitsch@ptb.de>, Patrick Schuenke <patrick.schuenke@ptb.de>, Felix Zimmermann <felix.zimmermann@ptb.de>, David Schote <david.schote@ptb.de>, Sherine Brahma <sherine.brahma@ptb.de>, Mara Guastini <mara.guastini@ptb.de>, Johannes Hammacher <johannnes.hammacher@ptb.de>, Stefan Martin <stefan.martin@ptb.de>, Andreas Kofler <andreas.kofler@ptb.de>, Catarina Redshaw Kranich <catarina.redshaw-kranich@ptb.de>
Project-URL: Documentation, https://ptb-mr.github.io/mrpro/
Keywords: MRI,qMRI,medical imaging,physics-informed learning,model-based reconstruction,quantitative,signal models,machine learning,deep learning,reconstruction,processing,Pulseq,PyTorch
Classifier: License :: OSI Approved :: Apache Software License
Classifier: Programming Language :: Python
Classifier: Programming Language :: Python :: 3.10
Classifier: Programming Language :: Python :: 3.11
Classifier: Programming Language :: Python :: 3.12
Classifier: Programming Language :: Python :: 3.13
Classifier: Programming Language :: Python :: 3 :: Only
Requires-Python: <3.14,>=3.10
License-File: LICENSE
Requires-Dist: numpy<3.0,>=1.23
Requires-Dist: torch>=2.3.1
Requires-Dist: ismrmrd>=1.14.1
Requires-Dist: einops>=0.7.0
Requires-Dist: pydicom>=3.0.1
Requires-Dist: pypulseq>=1.4.2
Requires-Dist: pytorch-finufft>=0.1.0
Requires-Dist: cufinufft>=2.4.1; platform_system == "Linux"
Requires-Dist: scipy>=1.12
Requires-Dist: ptwt<1.0,>=0.1.8
Requires-Dist: torchvision>=0.18.1
Requires-Dist: tqdm>=4.60.0
Requires-Dist: typing-extensions>=4.12
Requires-Dist: platformdirs>=4.0
Requires-Dist: requests>=2.25
Provides-Extra: tests
Requires-Dist: coverage; extra == "tests"
Requires-Dist: codecov; extra == "tests"
Requires-Dist: pre-commit; extra == "tests"
Requires-Dist: pytest; extra == "tests"
Requires-Dist: pytest-cov; extra == "tests"
Requires-Dist: pytest-xdist; extra == "tests"
Provides-Extra: docs
Requires-Dist: mrpro[notebooks]; extra == "docs"
Requires-Dist: sphinx<8.2,>=8.1; extra == "docs"
Requires-Dist: sphinx_rtd_theme<3.1,>=3.0; extra == "docs"
Requires-Dist: sphinx-pyproject<0.4,>=0.3; extra == "docs"
Requires-Dist: myst-nb<1.3,>=1.2; extra == "docs"
Requires-Dist: sphinx-mathjax-offline<0.1; extra == "docs"
Requires-Dist: sphinx_github_style<1.3,>=1.2; extra == "docs"
Requires-Dist: sphinx-autodoc-typehints<3.1,>=3; extra == "docs"
Requires-Dist: sphinx-copybutton<0.6,>=0.5; extra == "docs"
Requires-Dist: sphinx-last-updated-by-git<0.4,>=0.3; extra == "docs"
Provides-Extra: notebooks
Requires-Dist: zenodo_get>=2.0; extra == "notebooks"
Requires-Dist: ipykernel; extra == "notebooks"
Requires-Dist: ipywidgets; extra == "notebooks"
Requires-Dist: jupytext; extra == "notebooks"
Requires-Dist: matplotlib; extra == "notebooks"
Requires-Dist: cmap; extra == "notebooks"
Provides-Extra: dev
Requires-Dist: mrpro[docs,tests]; extra == "dev"
Dynamic: license-file
